storage_tools/__init__.py
storage_tools/_nbdev.py
storage_tools/cli.py
storage_tools/core.py
storage_tools-0.0.5.dist-info/LICENSE
storage_tools-0.0.5.dist-info/METADATA
storage_tools-0.0.5.dist-info/WHEEL
storage_tools-0.0.5.dist-info/entry_points.txt
storage_tools-0.0.5.dist-info/top_level.txt
storage_tools-0.0.5.dist-info/RECORD
