Metadata-Version: 2.1
Name: storage-tools
Version: 0.0.5
Summary: Make it easy to work with local or cloud storage as part of a data science workflow
Home-page: https://github.com/pete88b/storage_tools/tree/main/
Author: Peter Butterfill
Author-email: peter.butterfill@gmail.com
License: Apache Software License 2.0
Keywords: azure aws gcp storage
Platform: UNKNOWN
Classifier: Development Status :: 3 - Alpha
Classifier: Intended Audience :: Developers
Classifier: License :: OSI Approved :: Apache Software License
Classifier: Natural Language :: English
Classifier: Programming Language :: Python :: 3.6
Classifier: Programming Language :: Python :: 3.7
Classifier: Programming Language :: Python :: 3.8
Requires-Python: >=3.6
Requires-Dist: fastcore
Requires-Dist: boto3
Requires-Dist: azure-storage-blob
